README.md
setup.cfg
setup.py
seampy/__init__.py
seampy/amplitudes.py
seampy/integrands.py
seampy/solver.py
seampy/tools.py
seampy.egg-info/PKG-INFO
seampy.egg-info/SOURCES.txt
seampy.egg-info/dependency_links.txt
seampy.egg-info/requires.txt
seampy.egg-info/top_level.txt