Metadata-Version: 2.1
Name: seampy
Version: 1.0.0
Summary: Scattering Equations AMplitudes with PYthon
Home-page: https://github.com/GDeLaurentis/seampy
Author: Giuseppe De Laurentis
Author-email: g.dl@hotmail.it
License: GNU General Public License v3.0
Download-URL: https://github.com/GDeLaurentis/seampy/archive/v1.0.0.tar.gz
Keywords: Scattering Equations,Numerical Amplitudes,Tree Level,CHY Formalism
Platform: UNKNOWN
Classifier: Development Status :: 4 - Beta
Classifier: Intended Audience :: Science/Research
Classifier: Topic :: Scientific/Engineering :: Physics
Classifier: License :: OSI Approved :: GNU General Public License v3 (GPLv3)
Classifier: Programming Language :: Python :: 2.7
